.DS_Store
sreg/__init__.py
sreg/check_cluster.py
sreg/core.py
sreg/data_check.py
sreg/data_transfer.py
sreg/dgp_cluster.py
sreg/dgp_obs.py
sreg/dgp_po.py
sreg/dgp_rubin.py
sreg/dgp_strata.py
sreg/dgp_treatment.py
sreg/first_test.py
sreg/lin_adj.py
sreg/lm.py
sreg/output.py
sreg/pi_hat.py
sreg/result.py
sreg/sreg_script.py
sreg/subsample_filter.py
sreg/tau_hat.py
sreg/var_hat.py
sreg/data/AEJapp.csv
sreg-1.0.1.dist-info/METADATA
sreg-1.0.1.dist-info/WHEEL
sreg-1.0.1.dist-info/top_level.txt
sreg-1.0.1.dist-info/RECORD
