Metadata-Version: 2.1
Name: sreg
Version: 1.0.1
Summary: Stratified Randomized Experiments
Home-page: https://github.com/jutrifonov/sreg.py
Author: Juri Trifonov, Yuehao Bai, Azeem Shaikh, Max Tabord-Meehan
Author-email: jutrifonov@uchicago.edu
Classifier: Programming Language :: Python :: 3
Classifier: License :: OSI Approved :: MIT License
Classifier: Operating System :: OS Independent
Requires-Python: >=3.6
Requires-Dist: numpy (>=1.15.0)
Requires-Dist: pandas (>=0.23.0)
Requires-Dist: scipy (>=1.1.0)
Requires-Dist: statsmodels (>=0.14.2)
